<annotation>
	<folder></folder>
	<filename>maksssksksss30_png.rf.46bb059c5199cb2a12dd7381b734e567.jpg</filename>
	<path>maksssksksss30_png.rf.46bb059c5199cb2a12dd7381b734e567.jpg</path>
	<source>
		<database>roboflow.ai</database>
	</source>
	<size>
		<width>29</width>
		<height>25</height>
		<depth>3</depth>
	</size>
	<segmented>0</segmented>
	<object>
		<name>with_mask</name>
		<pose>Unspecified</pose>
		<truncated>0</truncated>
		<difficult>0</difficult>
		<occluded>0</occluded>
		<bndbox>
			<xmin>1</xmin>
			<xmax>30</xmax>
			<ymin>2</ymin>
			<ymax>26</ymax>
		</bndbox>
	</object>
</annotation>
