<annotation>
	<folder></folder>
	<filename>maksssksksss253_png.rf.5bb8d1e2767445543dc684182e0c60ea.jpg</filename>
	<path>maksssksksss253_png.rf.5bb8d1e2767445543dc684182e0c60ea.jpg</path>
	<source>
		<database>roboflow.ai</database>
	</source>
	<size>
		<width>16</width>
		<height>20</height>
		<depth>3</depth>
	</size>
	<segmented>0</segmented>
	<object>
		<name>with_mask</name>
		<pose>Unspecified</pose>
		<truncated>0</truncated>
		<difficult>0</difficult>
		<occluded>0</occluded>
		<bndbox>
			<xmin>1</xmin>
			<xmax>17</xmax>
			<ymin>1</ymin>
			<ymax>21</ymax>
		</bndbox>
	</object>
</annotation>
