<annotation>
	<folder></folder>
	<filename>maksssksksss696_png.rf.5cef4aa617619e423fe0a1063138f268.jpg</filename>
	<path>maksssksksss696_png.rf.5cef4aa617619e423fe0a1063138f268.jpg</path>
	<source>
		<database>roboflow.ai</database>
	</source>
	<size>
		<width>7</width>
		<height>20</height>
		<depth>3</depth>
	</size>
	<segmented>0</segmented>
	<object>
		<name>without_mask</name>
		<pose>Unspecified</pose>
		<truncated>0</truncated>
		<difficult>0</difficult>
		<occluded>0</occluded>
		<bndbox>
			<xmin>1</xmin>
			<xmax>8</xmax>
			<ymin>1</ymin>
			<ymax>21</ymax>
		</bndbox>
	</object>
</annotation>
