<annotation>
	<folder></folder>
	<filename>maksssksksss65_png.rf.65f7351fd9136a5b35d08597037bd4c5.jpg</filename>
	<path>maksssksksss65_png.rf.65f7351fd9136a5b35d08597037bd4c5.jpg</path>
	<source>
		<database>roboflow.ai</database>
	</source>
	<size>
		<width>39</width>
		<height>44</height>
		<depth>3</depth>
	</size>
	<segmented>0</segmented>
	<object>
		<name>with_mask</name>
		<pose>Unspecified</pose>
		<truncated>0</truncated>
		<difficult>0</difficult>
		<occluded>0</occluded>
		<bndbox>
			<xmin>1</xmin>
			<xmax>40</xmax>
			<ymin>2</ymin>
			<ymax>45</ymax>
		</bndbox>
	</object>
</annotation>
