<annotation>
	<folder></folder>
	<filename>maksssksksss293_png.rf.7aa8ec761d545aeed33a7a7bed2d5c1c.jpg</filename>
	<path>maksssksksss293_png.rf.7aa8ec761d545aeed33a7a7bed2d5c1c.jpg</path>
	<source>
		<database>roboflow.ai</database>
	</source>
	<size>
		<width>55</width>
		<height>52</height>
		<depth>3</depth>
	</size>
	<segmented>0</segmented>
	<object>
		<name>with_mask</name>
		<pose>Unspecified</pose>
		<truncated>0</truncated>
		<difficult>0</difficult>
		<occluded>0</occluded>
		<bndbox>
			<xmin>1</xmin>
			<xmax>56</xmax>
			<ymin>1</ymin>
			<ymax>53</ymax>
		</bndbox>
	</object>
</annotation>
