<annotation>
	<folder></folder>
	<filename>maksssksksss19_png.rf.60ba4fe12b25b70c726cdd048dfa157f.jpg</filename>
	<path>maksssksksss19_png.rf.60ba4fe12b25b70c726cdd048dfa157f.jpg</path>
	<source>
		<database>roboflow.ai</database>
	</source>
	<size>
		<width>79</width>
		<height>71</height>
		<depth>3</depth>
	</size>
	<segmented>0</segmented>
	<object>
		<name>with_mask</name>
		<pose>Unspecified</pose>
		<truncated>0</truncated>
		<difficult>0</difficult>
		<occluded>0</occluded>
		<bndbox>
			<xmin>2</xmin>
			<xmax>80</xmax>
			<ymin>1</ymin>
			<ymax>72</ymax>
		</bndbox>
	</object>
</annotation>
