<annotation>
	<folder></folder>
	<filename>maksssksksss630_png.rf.f27a0ff42f9410c8d374ee29ef20a608.jpg</filename>
	<path>maksssksksss630_png.rf.f27a0ff42f9410c8d374ee29ef20a608.jpg</path>
	<source>
		<database>roboflow.ai</database>
	</source>
	<size>
		<width>59</width>
		<height>106</height>
		<depth>3</depth>
	</size>
	<segmented>0</segmented>
	<object>
		<name>with_mask</name>
		<pose>Unspecified</pose>
		<truncated>0</truncated>
		<difficult>0</difficult>
		<occluded>0</occluded>
		<bndbox>
			<xmin>2</xmin>
			<xmax>60</xmax>
			<ymin>2</ymin>
			<ymax>107</ymax>
		</bndbox>
	</object>
</annotation>
