<annotation>
	<folder></folder>
	<filename>maksssksksss251_png.rf.fa710079372382d220c3da9e97e01edb.jpg</filename>
	<path>maksssksksss251_png.rf.fa710079372382d220c3da9e97e01edb.jpg</path>
	<source>
		<database>roboflow.ai</database>
	</source>
	<size>
		<width>20</width>
		<height>21</height>
		<depth>3</depth>
	</size>
	<segmented>0</segmented>
	<object>
		<name>without_mask</name>
		<pose>Unspecified</pose>
		<truncated>0</truncated>
		<difficult>0</difficult>
		<occluded>0</occluded>
		<bndbox>
			<xmin>2</xmin>
			<xmax>21</xmax>
			<ymin>2</ymin>
			<ymax>22</ymax>
		</bndbox>
	</object>
</annotation>
