<annotation>
	<folder></folder>
	<filename>maksssksksss240_png.rf.c16da04b6c450c16c54b36f8c6a4093c.jpg</filename>
	<path>maksssksksss240_png.rf.c16da04b6c450c16c54b36f8c6a4093c.jpg</path>
	<source>
		<database>roboflow.ai</database>
	</source>
	<size>
		<width>14</width>
		<height>13</height>
		<depth>3</depth>
	</size>
	<segmented>0</segmented>
	<object>
		<name>without_mask</name>
		<pose>Unspecified</pose>
		<truncated>0</truncated>
		<difficult>0</difficult>
		<occluded>0</occluded>
		<bndbox>
			<xmin>1</xmin>
			<xmax>15</xmax>
			<ymin>1</ymin>
			<ymax>14</ymax>
		</bndbox>
	</object>
</annotation>
